{
  "OnInitSequece": [],
  "OnStartSequece": [
    {
      "TaskList": [
        {
          "$type": "RPG.GameCore.LevelPerformanceInitialize",
          "PerformanceType": "D",
          "AreaPrefabPath": "Story/Discussion/Mission/8021131/DS802113104.prefab",
          "CreateCharacterList": [
            {
              "CharacterUniqueName": "W2_Beast02_01_C00",
              "AvatarID": "NPC_Monster_W2_Beast02_01",
              "AreaName": "DS802113104.prefab"
            }
          ],
          "CaptureNPCList": [],
          "HideNPC": true,
          "EntityVisiableList": [],
          "HideProp": true,
          "HideLocalPlayer": true,
          "UseNewStreamingSourceType": false,
          "StreamingSourcesInBlackMask": [],
          "StreamingSourcesAfterBlackMask": [],
          "MarkStreamingItems": []
        },
        {
          "$type": "RPG.GameCore.PlayTimeline",
          "TimelineName": "Story/Discussion/Mission/8021131/DS80211310401.playable",
          "Type": "Discussion",
          "Parameters": []
        },
        {
          "$type": "RPG.GameCore.EndPerformance"
        }
      ]
    },
    {
      "TaskList": [
        {
          "$type": "RPG.GameCore.WaitPerformanceEnd"
        },
        {
          "$type": "RPG.GameCore.FinishLevelGraph"
        }
      ]
    }
  ],
  "Type": "PerformanceD"
}