{
  "OnInitSequece": [],
  "OnStartSequece": [
    {
      "TaskList": [
        {
          "$type": "RPG.GameCore.PropStateChangeListenerConfig",
          "ToState": "Open",
          "FromAnyState": true,
          "OnChange": [
            {
              "$type": "RPG.GameCore.PlayMissionTalk",
              "SimpleTalkList": [
                {
                  "TalkSentenceID": 407131107,
                  "ProtectTime": 2
                }
              ]
            }
          ],
          "TargetType": {
            "$type": "RPG.GameCore.TargetFetchAdvPropEx",
            "FetchType": "SinglePropByPropID",
            "SinglePropID": {
              "GroupID": {
                "IsDynamic": false,
                "FixedValue": {
                  "Value": 2
                }
              },
              "ID": {
                "IsDynamic": false,
                "FixedValue": {
                  "Value": 300001
                }
              }
            }
          }
        }
      ]
    },
    {
      "TaskList": [
        {
          "$type": "RPG.GameCore.PropStateChangeListenerConfig",
          "ToState": "Open",
          "FromAnyState": true,
          "OnChange": [
            {
              "$type": "RPG.GameCore.PlayMissionTalk",
              "SimpleTalkList": [
                {
                  "TalkSentenceID": 407131106,
                  "ProtectTime": 2
                }
              ]
            }
          ],
          "TargetType": {
            "$type": "RPG.GameCore.TargetFetchAdvPropEx",
            "FetchType": "SinglePropByPropID",
            "SinglePropID": {
              "GroupID": {
                "IsDynamic": false,
                "FixedValue": {
                  "Value": 2
                }
              },
              "ID": {
                "IsDynamic": false,
                "FixedValue": {
                  "Value": 300002
                }
              }
            }
          }
        }
      ]
    },
    {
      "TaskList": [
        {
          "$type": "RPG.GameCore.PropStateChangeListenerConfig",
          "ToState": "Open",
          "FromAnyState": true,
          "OnChange": [
            {
              "$type": "RPG.GameCore.PlayMissionTalk",
              "SimpleTalkList": [
                {
                  "TalkSentenceID": 407131105,
                  "ProtectTime": 2
                }
              ]
            }
          ],
          "TargetType": {
            "$type": "RPG.GameCore.TargetFetchAdvPropEx",
            "FetchType": "SinglePropByPropID",
            "SinglePropID": {
              "GroupID": {
                "IsDynamic": false,
                "FixedValue": {
                  "Value": 2
                }
              },
              "ID": {
                "IsDynamic": false,
                "FixedValue": {
                  "Value": 300003
                }
              }
            }
          }
        }
      ]
    },
    {
      "TaskList": [
        {
          "$type": "RPG.GameCore.PropStateChangeListenerConfig",
          "ToState": "Open",
          "FromAnyState": true,
          "OnChange": [
            {
              "$type": "RPG.GameCore.PlayMissionTalk",
              "SimpleTalkList": [
                {
                  "TalkSentenceID": 407131104,
                  "ProtectTime": 2
                }
              ]
            }
          ],
          "TargetType": {
            "$type": "RPG.GameCore.TargetFetchAdvPropEx",
            "FetchType": "SinglePropByPropID",
            "SinglePropID": {
              "GroupID": {
                "IsDynamic": false,
                "FixedValue": {
                  "Value": 2
                }
              },
              "ID": {
                "IsDynamic": false,
                "FixedValue": {
                  "Value": 300004
                }
              }
            }
          }
        }
      ]
    }
  ]
}