{
  "OnInitSequece": [],
  "OnStartSequece": [
    {
      "TaskList": [
        {
          "$type": "RPG.GameCore.CollectDataConditions",
          "TaskIDList": [
            404020904
          ],
          "PerformanceIDList": []
        },
        {
          "$type": "RPG.GameCore.PredicateTaskList",
          "Predicate": {
            "$type": "RPG.GameCore.ByCompareSubMissionState",
            "SubMissionID": 404020904,
            "SubMissionState": "Started"
          },
          "SuccessTaskList": [
            {
              "$type": "RPG.GameCore.AddMenuItem",
              "MenuIconType": "SecretMissionIcon",
              "MenuItemID": 404020904,
              "DialoguePath": "Config/Level/NPCDialogue/P10202/F10202002_G14/DialogueItem402020904_F10202002_G14_N400001.json",
              "ExtraInfo": 2,
              "MissionID": 404020904
            }
          ]
        }
      ]
    }
  ]
}