{
  "GroupGUID": "5d4f1406-4d56-41ed-a199-0b8a49c89564",
  "GroupName": "MainMission4072012_Wave1_Point1",
  "Category": "Mission",
  "AreaAnchorName": "LevelArea_P44201_F44201002_G24",
  "SaveType": "Reset",
  "LoadCondition": {
    "Conditions": [
      {
        "Type": "SubMission",
        "ID": 407201201
      }
    ]
  },
  "UnloadCondition": {
    "Conditions": [
      {
        "Type": "SubMission",
        "Phase": "Finish",
        "ID": 407201201
      }
    ]
  },
  "OwnerMainMissionID": 4072012,
  "GroupStateList": [],
  "ConflictIDList": [],
  "AnchorList": [],
  "MonsterList": [],
  "PropList": [
    {
      "PropID": 111,
      "IsOverrideInitLevelGraph": true,
      "InitLevelGraph": "Config/Level/Raid/44201_Raid/Maze_InvisibleMonsterRaid_RaidTest_TriggerFinish.json",
      "ValueSource": {
        "Values": [
          {
            "$type": "RPG.GameCore.SharedString",
            "Value": "Talk_407201201",
            "Key": "Raid44201_UITriggerFinish_CustomString"
          }
        ]
      },
      "Trigger": {
        "Radius": 4.5,
        "DimX": 1,
        "DimY": 1,
        "DimZ": 1,
        "PointList": []
      },
      "CustomTriggerMap": {},
      "BridgeStateRotations": [],
      "DialogueGroups": [],
      "TalkDialogGroupIDList": [],
      "ServerInteractVerificationIDList": [],
      "Name": "Prop1",
      "RotY": 90,
      "ID": 300001,
      "PosX": 12.339,
      "PosY": 18.195,
      "PosZ": -13.4
    }
  ],
  "DistrictList": [],
  "WaypointList": [],
  "PathwayList": [],
  "BattleAreaList": [],
  "NPCList": [],
  "CrowdList": [],
  "PedestrianList": [],
  "SmartObjectList": []
}