{
  "GroupGUID": "38d042f4-2a7b-40d8-a409-5be49a14edc2",
  "GroupName": "MainMission2030301_New Group",
  "Category": "Mission",
  "AreaAnchorName": "LevelArea_P10305_F10305001_G88",
  "SaveType": "Reset",
  "IsPendedUnload": true,
  "OwnerMainMissionID": 2030301,
  "ValueSource": {},
  "ConflictIDList": [],
  "IsHoyoGroup": true,
  "HoYoGroupType": "Container",
  "ConflictWhiteList": [],
  "TagContainer": {},
  "AnchorList": [],
  "MonsterList": [],
  "PropList": [],
  "DistrictList": [],
  "WaypointList": [],
  "PathwayList": [],
  "BattleAreaList": [],
  "NPCList": [
    {
      "NPCID": 1007,
      "ValueSource": {},
      "DialogueGroups": [],
      "ServerInteractVerificationIDList": [],
      "BoardShowList": [
        8
      ],
      "TalkDialogGroupIDList": [],
      "DefaultIdleFreeStyleMotionID": 310070000,
      "InitialHiddenNodeList": [],
      "Dialog": {
        "LevelGraph": "Config/Level/NPCDialogue/P10305/F10305001_G88/DialogueMain_F10305001_G88_N400001.json",
        "PackList": [],
        "EnableCondition": {
          "Conditions": [
            {
              "Type": "SubMission",
              "Phase": "Finish",
              "ID": 203030103
            }
          ]
        }
      },
      "TagContainer": {},
      "CameraCenterEntityList": [],
      "SpawnConfig": {
        "EntitySpawnConfig": {}
      },
      "TriggerValidGuest": {},
      "Name": "NPC1",
      "RotY": 340.5859,
      "ID": 400001,
      "PosX": -28.3,
      "PosY": 7.549002,
      "PosZ": -455.24
    },
    {
      "NPCID": 13226,
      "ValueSource": {},
      "DialogueGroups": [],
      "ServerInteractVerificationIDList": [],
      "BoardShowList": [],
      "OverrideNPCName": {
        "Hash": -352251670
      },
      "TalkDialogGroupIDList": [],
      "InitialHiddenNodeList": [],
      "Dialog": {
        "LevelGraph": "Config/Level/NPCDialogue/P10305/F10305001_G88/DialogueMain_F10305001_G88_N400002.json",
        "PackList": []
      },
      "TagContainer": {},
      "CameraCenterEntityList": [],
      "SpawnConfig": {
        "EntitySpawnConfig": {}
      },
      "TriggerValidGuest": {},
      "Name": "NPC2",
      "ID": 400002,
      "PosX": -24.681,
      "PosY": 7.540004,
      "PosZ": -438.1
    }
  ],
  "CrowdList": [],
  "PedestrianList": [],
  "SmartObjectList": []
}