{
  "OnInitSequece": [],
  "OnStartSequece": [
    {
      "TaskList": [
        {
          "$type": "RPG.GameCore.AdvOnButtonPressed",
          "ButtonName": "Lock",
          "OnPressedCallback": [
            {
              "$type": "RPG.GameCore.ToastPile",
              "DescTextID": {
                "Hash": -245997968
              },
              "DescTextKey": {
                "Custom": true,
                "Key": "LockToastPile"
              }
            }
          ]
        }
      ]
    },
    {
      "TaskList": [
        {
          "$type": "RPG.GameCore.PropStateChangeListenerConfig",
          "ToState": "Open",
          "FromAnyState": true,
          "OnChange": [
            {
              "$type": "RPG.GameCore.TriggerEntityEvent",
              "EventName": {
                "Value": "Self_EnableInteract"
              },
              "InstanceID": {
                "IsDynamic": false,
                "FixedValue": {
                  "Value": 0
                }
              }
            },
            {
              "$type": "RPG.GameCore.TriggerEntityEvent",
              "EventName": {
                "Value": "Self_DisableLockInteract"
              },
              "InstanceID": {
                "IsDynamic": false,
                "FixedValue": {
                  "Value": 0
                }
              }
            },
            {
              "$type": "RPG.GameCore.AdvEnableTrigger",
              "TargetType": {
                "$type": "RPG.GameCore.TargetFetchAdvPropEx"
              },
              "IsEnable": true,
              "TriggerName": "ExitTrigger"
            },
            {
              "$type": "RPG.GameCore.TriggerEntityEvent",
              "EventName": {
                "Value": "Self_TriggerClose"
              },
              "InstanceID": {
                "IsDynamic": false,
                "FixedValue": {
                  "Value": 0
                }
              }
            }
          ],
          "TargetType": {
            "$type": "RPG.GameCore.TargetFetchAdvPropEx"
          }
        }
      ]
    },
    {
      "TaskList": [
        {
          "$type": "RPG.GameCore.PropStateChangeListenerConfig",
          "FromState": "Open",
          "FromAnyState": true,
          "OnChange": [
            {
              "$type": "RPG.GameCore.TriggerEntityEvent",
              "EventName": {
                "Value": "Self_DisableInteract"
              },
              "InstanceID": {
                "IsDynamic": false,
                "FixedValue": {
                  "Value": 0
                }
              }
            },
            {
              "$type": "RPG.GameCore.TriggerEntityEvent",
              "EventName": {
                "Value": "Self_EnableLockInteract"
              },
              "InstanceID": {
                "IsDynamic": false,
                "FixedValue": {
                  "Value": 0
                }
              }
            },
            {
              "$type": "RPG.GameCore.AdvEnableTrigger",
              "TargetType": {
                "$type": "RPG.GameCore.TargetFetchAdvPropEx"
              },
              "TriggerName": "ExitTrigger"
            },
            {
              "$type": "RPG.GameCore.TriggerEntityEvent",
              "EventName": {
                "Value": "Self_TriggerClose"
              },
              "InstanceID": {
                "IsDynamic": false,
                "FixedValue": {
                  "Value": 0
                }
              }
            }
          ],
          "TargetType": {
            "$type": "RPG.GameCore.TargetFetchAdvPropEx"
          }
        }
      ]
    },
    {
      "TaskList": [
        {
          "$type": "RPG.GameCore.PropStateChangeListenerConfig",
          "FromState": "Open",
          "ToState": "Locked",
          "FromAnyState": true,
          "OnChange": [
            {
              "$type": "RPG.GameCore.TriggerEntityEvent",
              "EventName": {
                "Value": "Self_DisableInteract"
              },
              "InstanceID": {
                "IsDynamic": false,
                "FixedValue": {
                  "Value": 0
                }
              }
            },
            {
              "$type": "RPG.GameCore.TriggerEntityEvent",
              "EventName": {
                "Value": "Self_DisableLockInteract"
              },
              "InstanceID": {
                "IsDynamic": false,
                "FixedValue": {
                  "Value": 0
                }
              }
            },
            {
              "$type": "RPG.GameCore.AdvEnableTrigger",
              "TargetType": {
                "$type": "RPG.GameCore.TargetFetchAdvPropEx"
              },
              "TriggerName": "ExitTrigger"
            },
            {
              "$type": "RPG.GameCore.TriggerEntityEvent",
              "EventName": {
                "Value": "Self_TriggerOpen"
              },
              "InstanceID": {
                "IsDynamic": false,
                "FixedValue": {
                  "Value": 0
                }
              }
            }
          ],
          "TargetType": {
            "$type": "RPG.GameCore.TargetFetchAdvPropEx"
          }
        }
      ]
    },
    {
      "TaskList": [
        {
          "$type": "RPG.GameCore.WaitGraphDynamicValueChange",
          "Name": "CanInteractInLock",
          "OnChange": [
            {
              "$type": "RPG.GameCore.PredicateTaskList",
              "Predicate": {
                "$type": "RPG.GameCore.ByAnd",
                "PredicateList": [
                  {
                    "$type": "RPG.GameCore.ByCompareGraphDynamicFloat",
                    "Name": "CanInteractInLock",
                    "Value": {
                      "IsDynamic": false,
                      "FixedValue": {
                        "Value": 1
                      }
                    },
                    "CompareType": "Equal"
                  },
                  {
                    "$type": "RPG.GameCore.ByComparePropState"
                  }
                ]
              },
              "SuccessTaskList": [
                {
                  "$type": "RPG.GameCore.TriggerEntityEvent",
                  "EventName": {
                    "Value": "Self_EnableLockInteract"
                  },
                  "InstanceID": {
                    "IsDynamic": false,
                    "FixedValue": {
                      "Value": 0
                    }
                  }
                }
              ],
              "FailedTaskList": [
                {
                  "$type": "RPG.GameCore.TriggerEntityEvent",
                  "EventName": {
                    "Value": "Self_DisableLockInteract"
                  },
                  "InstanceID": {
                    "IsDynamic": false,
                    "FixedValue": {
                      "Value": 0
                    }
                  }
                }
              ]
            }
          ]
        }
      ]
    },
    {
      "TaskList": [
        {
          "$type": "RPG.GameCore.WaitEntityEvent",
          "EventName": {
            "Value": "Self_TriggerOpen"
          },
          "OnEvent": [
            {
              "$type": "RPG.GameCore.SetGraphDynamicFloat",
              "Name": "Loc_IsOpen",
              "TargetIDs": [],
              "Value": {
                "IsDynamic": false,
                "FixedValue": {
                  "Value": 1
                }
              }
            }
          ],
          "InstanceID": {
            "IsDynamic": false,
            "FixedValue": {
              "Value": 0
            }
          }
        }
      ]
    },
    {
      "TaskList": [
        {
          "$type": "RPG.GameCore.WaitEntityEvent",
          "EventName": {
            "Value": "Self_TriggerClose"
          },
          "OnEvent": [
            {
              "$type": "RPG.GameCore.SetGraphDynamicFloat",
              "Name": "Loc_IsOpen",
              "TargetIDs": [],
              "Value": {
                "IsDynamic": false,
                "FixedValue": {
                  "Value": 0
                }
              }
            }
          ],
          "InstanceID": {
            "IsDynamic": false,
            "FixedValue": {
              "Value": 0
            }
          }
        }
      ]
    },
    {
      "TaskList": [
        {
          "$type": "RPG.GameCore.WaitGraphDynamicValueChange",
          "Name": "Loc_IsOpen",
          "OnChange": [
            {
              "$type": "RPG.GameCore.TriggerEntityEvent",
              "EventName": {
                "Value": "Self_Update"
              },
              "InstanceID": {
                "IsDynamic": false,
                "FixedValue": {
                  "Value": 0
                }
              }
            }
          ]
        }
      ]
    },
    {
      "TaskList": [
        {
          "$type": "RPG.GameCore.WaitEntityEvent",
          "EventName": {
            "Value": "Self_Update"
          },
          "OnEvent": [
            {
              "$type": "RPG.GameCore.GenericSwitchCase",
              "SwitchRef": {
                "$type": "RPG.GameCore.SwitchRefGraphDynamicFloat",
                "Name": "Loc_IsOpen"
              },
              "Cases": [
                {
                  "$type": "RPG.GameCore.NumberCaseContainer",
                  "Case": {
                    "IsDynamic": false,
                    "FixedValue": {
                      "Value": 1
                    }
                  },
                  "OnSuccess": [
                    {
                      "$type": "RPG.GameCore.AnimSetParameter",
                      "TargetType": {
                        "$type": "RPG.GameCore.TargetFetchAdvPropEx"
                      },
                      "ParameterName": "IsOpen",
                      "ParameterType": "Bool",
                      "Value": 1
                    },
                    {
                      "$type": "RPG.GameCore.GenericSwitchCase",
                      "SwitchRef": {
                        "$type": "RPG.GameCore.SwitchRefGraphDynamicFloat",
                        "Name": "OpenDir"
                      },
                      "Cases": [
                        {
                          "$type": "RPG.GameCore.NumberCaseContainer",
                          "Case": {
                            "IsDynamic": false,
                            "FixedValue": {
                              "Value": -1
                            }
                          },
                          "OnSuccess": [
                            {
                              "$type": "RPG.GameCore.PredicateTaskList",
                              "Predicate": {
                                "$type": "RPG.GameCore.ByAngle",
                                "From": {
                                  "$type": "RPG.GameCore.TargetFetchAdvPropEx"
                                },
                                "To": {
                                  "$type": "RPG.GameCore.TargetFetchAdvLocalPlayer"
                                },
                                "CompareType": "LessEqual",
                                "CompareValue": {
                                  "IsDynamic": false,
                                  "FixedValue": {
                                    "Value": 180
                                  }
                                }
                              },
                              "SuccessTaskList": [
                                {
                                  "$type": "RPG.GameCore.AnimSetParameter",
                                  "TargetType": {
                                    "$type": "RPG.GameCore.TargetFetchAdvPropEx"
                                  },
                                  "ParameterName": "IsForward",
                                  "ParameterType": "Bool",
                                  "Value": 1
                                }
                              ],
                              "FailedTaskList": [
                                {
                                  "$type": "RPG.GameCore.AnimSetParameter",
                                  "TargetType": {
                                    "$type": "RPG.GameCore.TargetFetchAdvPropEx"
                                  },
                                  "ParameterName": "IsForward",
                                  "ParameterType": "Bool"
                                }
                              ]
                            }
                          ]
                        },
                        {
                          "$type": "RPG.GameCore.NumberCaseContainer",
                          "Case": {
                            "IsDynamic": false,
                            "FixedValue": {
                              "Value": 0
                            }
                          },
                          "OnSuccess": [
                            {
                              "$type": "RPG.GameCore.AnimSetParameter",
                              "TargetType": {
                                "$type": "RPG.GameCore.TargetFetchAdvPropEx"
                              },
                              "ParameterName": "IsForward",
                              "ParameterType": "Bool"
                            }
                          ]
                        },
                        {
                          "$type": "RPG.GameCore.NumberCaseContainer",
                          "Case": {
                            "IsDynamic": false,
                            "FixedValue": {
                              "Value": 1
                            }
                          },
                          "OnSuccess": [
                            {
                              "$type": "RPG.GameCore.AnimSetParameter",
                              "TargetType": {
                                "$type": "RPG.GameCore.TargetFetchAdvPropEx"
                              },
                              "ParameterName": "IsForward",
                              "ParameterType": "Bool",
                              "Value": 1
                            }
                          ]
                        }
                      ]
                    }
                  ]
                },
                {
                  "$type": "RPG.GameCore.NumberCaseContainer",
                  "Case": {
                    "IsDynamic": false,
                    "FixedValue": {
                      "Value": 0
                    }
                  },
                  "OnSuccess": [
                    {
                      "$type": "RPG.GameCore.AnimSetParameter",
                      "TargetType": {
                        "$type": "RPG.GameCore.TargetFetchAdvPropEx"
                      },
                      "ParameterName": "IsOpen",
                      "ParameterType": "Bool"
                    }
                  ]
                }
              ]
            }
          ],
          "InstanceID": {
            "IsDynamic": false,
            "FixedValue": {
              "Value": 0
            }
          }
        }
      ]
    },
    {
      "TaskList": [
        {
          "$type": "RPG.GameCore.AdvOnButtonPressed",
          "ButtonName": "Interact",
          "OnPressedCallback": [
            {
              "$type": "RPG.GameCore.TriggerEntityEvent",
              "EventName": {
                "Value": "Self_TriggerOpen"
              },
              "InstanceID": {
                "IsDynamic": false,
                "FixedValue": {
                  "Value": 0
                }
              }
            }
          ]
        }
      ]
    },
    {
      "IsLoop": true,
      "TaskList": [
        {
          "$type": "RPG.GameCore.WaitAnimStateChange",
          "StateName": "Closed",
          "IsEnter": true
        },
        {
          "$type": "RPG.GameCore.SetNavMeshState",
          "TargetType": {
            "$type": "RPG.GameCore.TargetFetchAdvPropEx"
          },
          "Name": {
            "Value": "Closed"
          }
        },
        {
          "$type": "RPG.GameCore.TriggerEntityEvent",
          "EventName": {
            "Value": "Clt_OnClose"
          },
          "InstanceID": {
            "IsDynamic": false,
            "FixedValue": {
              "Value": 0
            }
          }
        },
        {
          "$type": "RPG.GameCore.SelectorConfig",
          "TaskList": [
            {
              "$type": "RPG.GameCore.PropStateExecute",
              "TargetType": {
                "$type": "RPG.GameCore.TargetFetchAdvPropEx"
              },
              "State": "Open",
              "Execute": [
                {
                  "$type": "RPG.GameCore.TriggerEntityEvent",
                  "EventName": {
                    "Value": "Self_EnableInteract"
                  },
                  "InstanceID": {
                    "IsDynamic": false,
                    "FixedValue": {
                      "Value": 0
                    }
                  }
                }
              ]
            }
          ]
        }
      ]
    },
    {
      "IsLoop": true,
      "TaskList": [
        {
          "$type": "RPG.GameCore.WaitAnimStateChange",
          "StateName": "Closed"
        },
        {
          "$type": "RPG.GameCore.TriggerEntityEvent",
          "EventName": {
            "Value": "Clt_OnOpen"
          },
          "InstanceID": {
            "IsDynamic": false,
            "FixedValue": {
              "Value": 0
            }
          }
        },
        {
          "$type": "RPG.GameCore.SelectorConfig",
          "TaskList": [
            {
              "$type": "RPG.GameCore.PropStateExecute",
              "TargetType": {
                "$type": "RPG.GameCore.TargetFetchAdvPropEx"
              },
              "State": "Open",
              "Execute": [
                {
                  "$type": "RPG.GameCore.TriggerEntityEvent",
                  "EventName": {
                    "Value": "Self_DisableInteract"
                  },
                  "InstanceID": {
                    "IsDynamic": false,
                    "FixedValue": {
                      "Value": 0
                    }
                  }
                }
              ]
            }
          ]
        }
      ]
    },
    {
      "IsLoop": true,
      "TaskList": [
        {
          "$type": "RPG.GameCore.WaitAnimStateChange",
          "StateName": "Opening01",
          "IsEnter": true
        },
        {
          "$type": "RPG.GameCore.SetNavMeshState",
          "TargetType": {
            "$type": "RPG.GameCore.TargetFetchAdvPropEx"
          },
          "Name": {
            "Value": "Open01"
          }
        }
      ]
    },
    {
      "IsLoop": true,
      "TaskList": [
        {
          "$type": "RPG.GameCore.WaitAnimStateChange",
          "StateName": "Opening02",
          "IsEnter": true
        },
        {
          "$type": "RPG.GameCore.SetNavMeshState",
          "TargetType": {
            "$type": "RPG.GameCore.TargetFetchAdvPropEx"
          },
          "Name": {
            "Value": "Open02"
          }
        }
      ]
    },
    {
      "TaskList": [
        {
          "$type": "RPG.GameCore.WaitEntityEvent",
          "EventName": {
            "Value": "Self_EnableInteract"
          },
          "OnEvent": [
            {
              "$type": "RPG.GameCore.PredicateTaskList",
              "Predicate": {
                "$type": "RPG.GameCore.ByCompareGraphDynamicFloat",
                "Name": "IsAutoDoor",
                "Value": {
                  "IsDynamic": false,
                  "FixedValue": {
                    "Value": 0
                  }
                },
                "CompareType": "Equal"
              },
              "SuccessTaskList": [
                {
                  "$type": "RPG.GameCore.AdvEnableButtons",
                  "TargetType": {
                    "$type": "RPG.GameCore.TargetFetchAdvPropEx"
                  },
                  "TriggerName": "InteractTrigger",
                  "ButtonsByName": [
                    "Interact"
                  ],
                  "IsEnable": true
                }
              ],
              "FailedTaskList": [
                {
                  "$type": "RPG.GameCore.AdvEnableTrigger",
                  "TargetType": {
                    "$type": "RPG.GameCore.TargetFetchAdvPropEx"
                  },
                  "IsEnable": true,
                  "TriggerName": "CloseToTrigger"
                }
              ]
            }
          ],
          "InstanceID": {
            "IsDynamic": false,
            "FixedValue": {
              "Value": 0
            }
          }
        }
      ]
    },
    {
      "TaskList": [
        {
          "$type": "RPG.GameCore.WaitEntityEvent",
          "EventName": {
            "Value": "Self_DisableInteract"
          },
          "OnEvent": [
            {
              "$type": "RPG.GameCore.PredicateTaskList",
              "Predicate": {
                "$type": "RPG.GameCore.ByCompareGraphDynamicFloat",
                "Name": "IsAutoDoor",
                "Value": {
                  "IsDynamic": false,
                  "FixedValue": {
                    "Value": 0
                  }
                },
                "CompareType": "Equal"
              },
              "SuccessTaskList": [
                {
                  "$type": "RPG.GameCore.AdvEnableButtons",
                  "TargetType": {
                    "$type": "RPG.GameCore.TargetFetchAdvPropEx"
                  },
                  "TriggerName": "InteractTrigger",
                  "ButtonsByName": [
                    "Interact"
                  ]
                }
              ],
              "FailedTaskList": [
                {
                  "$type": "RPG.GameCore.AdvEnableTrigger",
                  "TargetType": {
                    "$type": "RPG.GameCore.TargetFetchAdvPropEx"
                  },
                  "TriggerName": "CloseToTrigger"
                }
              ]
            }
          ],
          "InstanceID": {
            "IsDynamic": false,
            "FixedValue": {
              "Value": 0
            }
          }
        }
      ]
    },
    {
      "TaskList": [
        {
          "$type": "RPG.GameCore.WaitEntityEvent",
          "EventName": {
            "Value": "Clt_TriggerOpen"
          },
          "OnEvent": [
            {
              "$type": "RPG.GameCore.GenericSwitchCase",
              "SwitchRef": {
                "$type": "RPG.GameCore.SwitchRefPropState"
              },
              "Cases": [
                {
                  "$type": "RPG.GameCore.PropStateCaseContainer",
                  "OnSuccess": [
                    {
                      "$type": "RPG.GameCore.AdvClientChangePropState",
                      "TargetType": {
                        "$type": "RPG.GameCore.TargetFetchAdvPropEx"
                      },
                      "ToState": "Open"
                    }
                  ]
                },
                {
                  "$type": "RPG.GameCore.PropStateCaseContainer",
                  "Case": "Locked",
                  "OnSuccess": [
                    {
                      "$type": "RPG.GameCore.AdvClientChangePropState",
                      "TargetType": {
                        "$type": "RPG.GameCore.TargetFetchAdvPropEx"
                      },
                      "FromState": "Locked",
                      "ToState": "Open"
                    }
                  ]
                }
              ]
            }
          ],
          "InstanceID": {
            "IsDynamic": false,
            "FixedValue": {
              "Value": 0
            }
          }
        }
      ]
    },
    {
      "TaskList": [
        {
          "$type": "RPG.GameCore.WaitEntityEvent",
          "EventName": {
            "Value": "Clt_TriggerClose"
          },
          "OnEvent": [
            {
              "$type": "RPG.GameCore.GenericSwitchCase",
              "SwitchRef": {
                "$type": "RPG.GameCore.SwitchRefPropState"
              },
              "Cases": [
                {
                  "$type": "RPG.GameCore.PropStateCaseContainer",
                  "Case": "Open",
                  "OnSuccess": [
                    {
                      "$type": "RPG.GameCore.AdvClientChangePropState",
                      "TargetType": {
                        "$type": "RPG.GameCore.TargetFetchAdvPropEx"
                      },
                      "FromState": "Open"
                    }
                  ]
                },
                {
                  "$type": "RPG.GameCore.PropStateCaseContainer",
                  "Case": "Locked",
                  "OnSuccess": [
                    {
                      "$type": "RPG.GameCore.AdvClientChangePropState",
                      "TargetType": {
                        "$type": "RPG.GameCore.TargetFetchAdvPropEx"
                      },
                      "FromState": "Locked"
                    }
                  ]
                }
              ]
            }
          ],
          "InstanceID": {
            "IsDynamic": false,
            "FixedValue": {
              "Value": 0
            }
          }
        }
      ]
    },
    {
      "TaskList": [
        {
          "$type": "RPG.GameCore.WaitEntityEvent",
          "EventName": {
            "Value": "Clt_TriggerLock"
          },
          "OnEvent": [
            {
              "$type": "RPG.GameCore.GenericSwitchCase",
              "SwitchRef": {
                "$type": "RPG.GameCore.SwitchRefPropState"
              },
              "Cases": [
                {
                  "$type": "RPG.GameCore.PropStateCaseContainer",
                  "OnSuccess": [
                    {
                      "$type": "RPG.GameCore.AdvClientChangePropState",
                      "TargetType": {
                        "$type": "RPG.GameCore.TargetFetchAdvPropEx"
                      },
                      "ToState": "Locked"
                    }
                  ]
                },
                {
                  "$type": "RPG.GameCore.PropStateCaseContainer",
                  "Case": "Open",
                  "OnSuccess": [
                    {
                      "$type": "RPG.GameCore.AdvClientChangePropState",
                      "TargetType": {
                        "$type": "RPG.GameCore.TargetFetchAdvPropEx"
                      },
                      "FromState": "Open",
                      "ToState": "Locked"
                    }
                  ]
                }
              ]
            }
          ],
          "InstanceID": {
            "IsDynamic": false,
            "FixedValue": {
              "Value": 0
            }
          }
        }
      ]
    },
    {
      "TaskList": [
        {
          "$type": "RPG.GameCore.WaitEntityEvent",
          "EventName": {
            "Value": "CltSrv_TriggerOpen"
          },
          "OnEvent": [
            {
              "$type": "RPG.GameCore.GenericSwitchCase",
              "SwitchRef": {
                "$type": "RPG.GameCore.SwitchRefPropState"
              },
              "Cases": [
                {
                  "$type": "RPG.GameCore.PropStateCaseContainer",
                  "OnSuccess": [
                    {
                      "$type": "RPG.GameCore.PropReqInteract",
                      "TargetType": {
                        "$type": "RPG.GameCore.TargetFetchAdvPropEx"
                      },
                      "InteractID": {
                        "IsDynamic": false,
                        "FixedValue": {
                          "Value": 1010
                        }
                      }
                    }
                  ]
                },
                {
                  "$type": "RPG.GameCore.PropStateCaseContainer",
                  "Case": "Locked",
                  "OnSuccess": [
                    {
                      "$type": "RPG.GameCore.PropReqInteract",
                      "TargetType": {
                        "$type": "RPG.GameCore.TargetFetchAdvPropEx"
                      },
                      "InteractID": {
                        "IsDynamic": false,
                        "FixedValue": {
                          "Value": 1210
                        }
                      }
                    }
                  ]
                }
              ]
            }
          ],
          "InstanceID": {
            "IsDynamic": false,
            "FixedValue": {
              "Value": 0
            }
          }
        }
      ]
    },
    {
      "TaskList": [
        {
          "$type": "RPG.GameCore.WaitEntityEvent",
          "EventName": {
            "Value": "CltSrv_TriggerClose"
          },
          "OnEvent": [
            {
              "$type": "RPG.GameCore.GenericSwitchCase",
              "SwitchRef": {
                "$type": "RPG.GameCore.SwitchRefPropState"
              },
              "Cases": [
                {
                  "$type": "RPG.GameCore.PropStateCaseContainer",
                  "Case": "Open",
                  "OnSuccess": [
                    {
                      "$type": "RPG.GameCore.PropReqInteract",
                      "TargetType": {
                        "$type": "RPG.GameCore.TargetFetchAdvPropEx"
                      },
                      "InteractID": {
                        "IsDynamic": false,
                        "FixedValue": {
                          "Value": 1100
                        }
                      }
                    }
                  ]
                },
                {
                  "$type": "RPG.GameCore.PropStateCaseContainer",
                  "Case": "Locked",
                  "OnSuccess": [
                    {
                      "$type": "RPG.GameCore.PropReqInteract",
                      "TargetType": {
                        "$type": "RPG.GameCore.TargetFetchAdvPropEx"
                      },
                      "InteractID": {
                        "IsDynamic": false,
                        "FixedValue": {
                          "Value": 1200
                        }
                      }
                    }
                  ]
                }
              ]
            }
          ],
          "InstanceID": {
            "IsDynamic": false,
            "FixedValue": {
              "Value": 0
            }
          }
        }
      ]
    },
    {
      "TaskList": [
        {
          "$type": "RPG.GameCore.WaitEntityEvent",
          "EventName": {
            "Value": "CltSrv_TriggerLock"
          },
          "OnEvent": [
            {
              "$type": "RPG.GameCore.GenericSwitchCase",
              "SwitchRef": {
                "$type": "RPG.GameCore.SwitchRefPropState"
              },
              "Cases": [
                {
                  "$type": "RPG.GameCore.PropStateCaseContainer",
                  "OnSuccess": [
                    {
                      "$type": "RPG.GameCore.PropReqInteract",
                      "TargetType": {
                        "$type": "RPG.GameCore.TargetFetchAdvPropEx"
                      },
                      "InteractID": {
                        "IsDynamic": false,
                        "FixedValue": {
                          "Value": 1020
                        }
                      }
                    }
                  ]
                },
                {
                  "$type": "RPG.GameCore.PropStateCaseContainer",
                  "Case": "Open",
                  "OnSuccess": [
                    {
                      "$type": "RPG.GameCore.PropReqInteract",
                      "TargetType": {
                        "$type": "RPG.GameCore.TargetFetchAdvPropEx"
                      },
                      "InteractID": {
                        "IsDynamic": false,
                        "FixedValue": {
                          "Value": 1120
                        }
                      }
                    }
                  ]
                }
              ]
            }
          ],
          "InstanceID": {
            "IsDynamic": false,
            "FixedValue": {
              "Value": 0
            }
          }
        }
      ]
    },
    {
      "TaskList": [
        {
          "$type": "RPG.GameCore.LoopWaitEntityServerEvent"
        }
      ]
    },
    {
      "TaskList": [
        {
          "$type": "RPG.GameCore.LoopWaitEntityServerEvent"
        }
      ]
    },
    {
      "TaskList": [
        {
          "$type": "RPG.GameCore.LoopWaitEntityServerEvent"
        }
      ]
    },
    {
      "TaskList": [
        {
          "$type": "RPG.GameCore.WaitEntityEvent",
          "EventName": {
            "Value": "Self_EnableLockInteract"
          },
          "OnEvent": [
            {
              "$type": "RPG.GameCore.PredicateTaskList",
              "Predicate": {
                "$type": "RPG.GameCore.ByCompareGraphDynamicFloat",
                "Name": "CanInteractInLock",
                "Value": {
                  "IsDynamic": false,
                  "FixedValue": {
                    "Value": 1
                  }
                },
                "CompareType": "Equal"
              },
              "SuccessTaskList": [
                {
                  "$type": "RPG.GameCore.AdvEnableButtons",
                  "TargetType": {
                    "$type": "RPG.GameCore.TargetFetchAdvPropEx"
                  },
                  "TriggerName": "InteractTrigger",
                  "ButtonsByName": [
                    "Lock"
                  ],
                  "IsEnable": true
                }
              ],
              "FailedTaskList": [
                {
                  "$type": "RPG.GameCore.AdvEnableButtons",
                  "TargetType": {
                    "$type": "RPG.GameCore.TargetFetchAdvPropEx"
                  },
                  "TriggerName": "InteractTrigger",
                  "ButtonsByName": [
                    "Lock"
                  ]
                }
              ]
            }
          ],
          "InstanceID": {
            "IsDynamic": false,
            "FixedValue": {
              "Value": 0
            }
          }
        }
      ]
    },
    {
      "TaskList": [
        {
          "$type": "RPG.GameCore.WaitEntityEvent",
          "EventName": {
            "Value": "Self_DisableLockInteract"
          },
          "OnEvent": [
            {
              "$type": "RPG.GameCore.AdvEnableButtons",
              "TargetType": {
                "$type": "RPG.GameCore.TargetFetchAdvPropEx"
              },
              "TriggerName": "InteractTrigger",
              "ButtonsByName": [
                "Lock"
              ]
            }
          ],
          "InstanceID": {
            "IsDynamic": false,
            "FixedValue": {
              "Value": 0
            }
          }
        }
      ]
    },
    {
      "TaskList": [
        {
          "$type": "RPG.GameCore.AdvSetupCustomTaskTrigger",
          "TriggerName": "ExitTrigger",
          "OnEnter": [],
          "OnExit": [
            {
              "$type": "RPG.GameCore.TriggerEntityEvent",
              "EventName": {
                "Value": "Self_TriggerClose"
              },
              "InstanceID": {
                "IsDynamic": false,
                "FixedValue": {
                  "Value": 0
                }
              }
            }
          ],
          "IsOverrideValidGuestConfig": true,
          "OverridedValidGuestConfig": {}
        },
        {
          "$type": "RPG.GameCore.PredicateTaskList",
          "Predicate": {
            "$type": "RPG.GameCore.ByCompareGraphDynamicFloat",
            "Name": "IsAutoDoor",
            "Value": {
              "IsDynamic": false,
              "FixedValue": {
                "Value": 0
              }
            },
            "CompareType": "Equal"
          },
          "SuccessTaskList": [
            {
              "$type": "RPG.GameCore.AdvSetupButtonListTrigger",
              "TriggerName": "InteractTrigger",
              "ButtonsByName": [
                "Interact",
                "Lock"
              ],
              "ButtonConfigs": [],
              "IsOverrideValidGuestConfig": true,
              "OverridedValidGuestConfig": {}
            },
            {
              "$type": "RPG.GameCore.GenericSwitchCase",
              "SwitchRef": {
                "$type": "RPG.GameCore.SwitchRefPropState"
              },
              "Cases": [
                {
                  "$type": "RPG.GameCore.PropStateCaseContainer",
                  "OnSuccess": [
                    {
                      "$type": "RPG.GameCore.AdvEnableButtons",
                      "TargetType": {
                        "$type": "RPG.GameCore.TargetFetchAdvPropEx"
                      },
                      "TriggerName": "InteractTrigger",
                      "ButtonsByName": [
                        "Interact"
                      ]
                    },
                    {
                      "$type": "RPG.GameCore.AdvEnableTrigger",
                      "TargetType": {
                        "$type": "RPG.GameCore.TargetFetchAdvPropEx"
                      },
                      "TriggerName": "ExitTrigger"
                    },
                    {
                      "$type": "RPG.GameCore.TriggerEntityEvent",
                      "EventName": {
                        "Value": "Self_EnableLockInteract"
                      },
                      "InstanceID": {
                        "IsDynamic": false,
                        "FixedValue": {
                          "Value": 0
                        }
                      }
                    }
                  ]
                },
                {
                  "$type": "RPG.GameCore.PropStateCaseContainer",
                  "Case": "Open",
                  "OnSuccess": [
                    {
                      "$type": "RPG.GameCore.AdvEnableButtons",
                      "TargetType": {
                        "$type": "RPG.GameCore.TargetFetchAdvPropEx"
                      },
                      "TriggerName": "InteractTrigger",
                      "ButtonsByName": [
                        "Interact"
                      ],
                      "IsEnable": true
                    },
                    {
                      "$type": "RPG.GameCore.AdvEnableTrigger",
                      "TargetType": {
                        "$type": "RPG.GameCore.TargetFetchAdvPropEx"
                      },
                      "IsEnable": true,
                      "TriggerName": "ExitTrigger"
                    },
                    {
                      "$type": "RPG.GameCore.TriggerEntityEvent",
                      "EventName": {
                        "Value": "Self_DisableLockInteract"
                      },
                      "InstanceID": {
                        "IsDynamic": false,
                        "FixedValue": {
                          "Value": 0
                        }
                      }
                    }
                  ]
                },
                {
                  "$type": "RPG.GameCore.PropStateCaseContainer",
                  "Case": "Locked",
                  "OnSuccess": [
                    {
                      "$type": "RPG.GameCore.AdvEnableButtons",
                      "TargetType": {
                        "$type": "RPG.GameCore.TargetFetchAdvPropEx"
                      },
                      "TriggerName": "InteractTrigger",
                      "ButtonsByName": [
                        "Interact"
                      ]
                    },
                    {
                      "$type": "RPG.GameCore.AdvEnableTrigger",
                      "TargetType": {
                        "$type": "RPG.GameCore.TargetFetchAdvPropEx"
                      },
                      "TriggerName": "ExitTrigger"
                    },
                    {
                      "$type": "RPG.GameCore.TriggerEntityEvent",
                      "EventName": {
                        "Value": "Self_DisableLockInteract"
                      },
                      "InstanceID": {
                        "IsDynamic": false,
                        "FixedValue": {
                          "Value": 0
                        }
                      }
                    },
                    {
                      "$type": "RPG.GameCore.GenericSwitchCase",
                      "SwitchRef": {
                        "$type": "RPG.GameCore.SwitchRefGraphDynamicFloat",
                        "Name": "OpenDir"
                      },
                      "Cases": [
                        {
                          "$type": "RPG.GameCore.NumberCaseContainer",
                          "Case": {
                            "IsDynamic": false,
                            "FixedValue": {
                              "Value": -1
                            }
                          },
                          "OnSuccess": [
                            {
                              "$type": "RPG.GameCore.PredicateTaskList",
                              "Predicate": {
                                "$type": "RPG.GameCore.ByAngle",
                                "From": {
                                  "$type": "RPG.GameCore.TargetFetchAdvPropEx"
                                },
                                "To": {
                                  "$type": "RPG.GameCore.TargetFetchAdvLocalPlayer"
                                },
                                "CompareType": "LessEqual",
                                "CompareValue": {
                                  "IsDynamic": false,
                                  "FixedValue": {
                                    "Value": 180
                                  }
                                }
                              },
                              "SuccessTaskList": [
                                {
                                  "$type": "RPG.GameCore.AnimSetParameter",
                                  "TargetType": {
                                    "$type": "RPG.GameCore.TargetFetchAdvPropEx"
                                  },
                                  "ParameterName": "IsForward",
                                  "ParameterType": "Bool",
                                  "Value": 1
                                },
                                {
                                  "$type": "RPG.GameCore.PropTriggerAnimState",
                                  "AnimStateName": "Opened01",
                                  "TransitionDuration": 0,
                                  "TargetType": {
                                    "$type": "RPG.GameCore.TargetFetchAdvPropEx"
                                  }
                                },
                                {
                                  "$type": "RPG.GameCore.AnimSetParameter",
                                  "TargetType": {
                                    "$type": "RPG.GameCore.TargetFetchAdvPropEx"
                                  },
                                  "ParameterName": "IsOpen",
                                  "ParameterType": "Bool",
                                  "Value": 1
                                },
                                {
                                  "$type": "RPG.GameCore.SetGraphDynamicFloat",
                                  "Name": "Loc_IsOpen",
                                  "TargetIDs": [],
                                  "Value": {
                                    "IsDynamic": false,
                                    "FixedValue": {
                                      "Value": 1
                                    }
                                  }
                                }
                              ],
                              "FailedTaskList": [
                                {
                                  "$type": "RPG.GameCore.AnimSetParameter",
                                  "TargetType": {
                                    "$type": "RPG.GameCore.TargetFetchAdvPropEx"
                                  },
                                  "ParameterName": "IsForward",
                                  "ParameterType": "Bool"
                                },
                                {
                                  "$type": "RPG.GameCore.PropTriggerAnimState",
                                  "AnimStateName": "Opened02",
                                  "TransitionDuration": 0,
                                  "TargetType": {
                                    "$type": "RPG.GameCore.TargetFetchAdvPropEx"
                                  }
                                },
                                {
                                  "$type": "RPG.GameCore.AnimSetParameter",
                                  "TargetType": {
                                    "$type": "RPG.GameCore.TargetFetchAdvPropEx"
                                  },
                                  "ParameterName": "IsOpen",
                                  "ParameterType": "Bool",
                                  "Value": 1
                                },
                                {
                                  "$type": "RPG.GameCore.SetGraphDynamicFloat",
                                  "Name": "Loc_IsOpen",
                                  "TargetIDs": [],
                                  "Value": {
                                    "IsDynamic": false,
                                    "FixedValue": {
                                      "Value": 1
                                    }
                                  }
                                }
                              ]
                            }
                          ]
                        },
                        {
                          "$type": "RPG.GameCore.NumberCaseContainer",
                          "Case": {
                            "IsDynamic": false,
                            "FixedValue": {
                              "Value": 0
                            }
                          },
                          "OnSuccess": [
                            {
                              "$type": "RPG.GameCore.AnimSetParameter",
                              "TargetType": {
                                "$type": "RPG.GameCore.TargetFetchAdvPropEx"
                              },
                              "ParameterName": "IsForward",
                              "ParameterType": "Bool"
                            },
                            {
                              "$type": "RPG.GameCore.PropTriggerAnimState",
                              "AnimStateName": "Opened02",
                              "TransitionDuration": 0,
                              "TargetType": {
                                "$type": "RPG.GameCore.TargetFetchAdvPropEx"
                              }
                            },
                            {
                              "$type": "RPG.GameCore.AnimSetParameter",
                              "TargetType": {
                                "$type": "RPG.GameCore.TargetFetchAdvPropEx"
                              },
                              "ParameterName": "IsOpen",
                              "ParameterType": "Bool",
                              "Value": 1
                            },
                            {
                              "$type": "RPG.GameCore.SetGraphDynamicFloat",
                              "Name": "Loc_IsOpen",
                              "TargetIDs": [],
                              "Value": {
                                "IsDynamic": false,
                                "FixedValue": {
                                  "Value": 1
                                }
                              }
                            }
                          ]
                        },
                        {
                          "$type": "RPG.GameCore.NumberCaseContainer",
                          "Case": {
                            "IsDynamic": false,
                            "FixedValue": {
                              "Value": 1
                            }
                          },
                          "OnSuccess": [
                            {
                              "$type": "RPG.GameCore.AnimSetParameter",
                              "TargetType": {
                                "$type": "RPG.GameCore.TargetFetchAdvPropEx"
                              },
                              "ParameterName": "IsForward",
                              "ParameterType": "Bool",
                              "Value": 1
                            },
                            {
                              "$type": "RPG.GameCore.PropTriggerAnimState",
                              "AnimStateName": "Opened01",
                              "TransitionDuration": 0,
                              "TargetType": {
                                "$type": "RPG.GameCore.TargetFetchAdvPropEx"
                              }
                            },
                            {
                              "$type": "RPG.GameCore.AnimSetParameter",
                              "TargetType": {
                                "$type": "RPG.GameCore.TargetFetchAdvPropEx"
                              },
                              "ParameterName": "IsOpen",
                              "ParameterType": "Bool",
                              "Value": 1
                            },
                            {
                              "$type": "RPG.GameCore.SetGraphDynamicFloat",
                              "Name": "Loc_IsOpen",
                              "TargetIDs": [],
                              "Value": {
                                "IsDynamic": false,
                                "FixedValue": {
                                  "Value": 1
                                }
                              }
                            }
                          ]
                        }
                      ]
                    }
                  ]
                }
              ]
            }
          ],
          "FailedTaskList": [
            {
              "$type": "RPG.GameCore.AdvSetupButtonListTrigger",
              "TriggerName": "InteractTrigger",
              "ButtonsByName": [
                "Lock"
              ],
              "ButtonConfigs": [],
              "IsOverrideValidGuestConfig": true,
              "OverridedValidGuestConfig": {}
            },
            {
              "$type": "RPG.GameCore.AdvSetupCustomTaskTrigger",
              "TriggerName": "CloseToTrigger",
              "OnEnter": [
                {
                  "$type": "RPG.GameCore.TriggerEntityEvent",
                  "EventName": {
                    "Value": "Self_TriggerOpen"
                  },
                  "InstanceID": {
                    "IsDynamic": false,
                    "FixedValue": {
                      "Value": 0
                    }
                  }
                }
              ],
              "IsOverrideValidGuestConfig": true,
              "OverridedValidGuestConfig": {}
            },
            {
              "$type": "RPG.GameCore.GenericSwitchCase",
              "SwitchRef": {
                "$type": "RPG.GameCore.SwitchRefPropState"
              },
              "Cases": [
                {
                  "$type": "RPG.GameCore.PropStateCaseContainer",
                  "OnSuccess": [
                    {
                      "$type": "RPG.GameCore.AdvEnableTrigger",
                      "TargetType": {
                        "$type": "RPG.GameCore.TargetFetchAdvPropEx"
                      },
                      "TriggerName": "CloseToTrigger"
                    },
                    {
                      "$type": "RPG.GameCore.AdvEnableTrigger",
                      "TargetType": {
                        "$type": "RPG.GameCore.TargetFetchAdvPropEx"
                      },
                      "TriggerName": "ExitTrigger"
                    },
                    {
                      "$type": "RPG.GameCore.TriggerEntityEvent",
                      "EventName": {
                        "Value": "Self_EnableLockInteract"
                      },
                      "InstanceID": {
                        "IsDynamic": false,
                        "FixedValue": {
                          "Value": 0
                        }
                      }
                    }
                  ]
                },
                {
                  "$type": "RPG.GameCore.PropStateCaseContainer",
                  "Case": "Open",
                  "OnSuccess": [
                    {
                      "$type": "RPG.GameCore.AdvEnableTrigger",
                      "TargetType": {
                        "$type": "RPG.GameCore.TargetFetchAdvPropEx"
                      },
                      "IsEnable": true,
                      "TriggerName": "CloseToTrigger"
                    },
                    {
                      "$type": "RPG.GameCore.AdvEnableTrigger",
                      "TargetType": {
                        "$type": "RPG.GameCore.TargetFetchAdvPropEx"
                      },
                      "IsEnable": true,
                      "TriggerName": "ExitTrigger"
                    },
                    {
                      "$type": "RPG.GameCore.TriggerEntityEvent",
                      "EventName": {
                        "Value": "Self_DisableLockInteract"
                      },
                      "InstanceID": {
                        "IsDynamic": false,
                        "FixedValue": {
                          "Value": 0
                        }
                      }
                    }
                  ]
                },
                {
                  "$type": "RPG.GameCore.PropStateCaseContainer",
                  "Case": "Locked",
                  "OnSuccess": [
                    {
                      "$type": "RPG.GameCore.AdvEnableTrigger",
                      "TargetType": {
                        "$type": "RPG.GameCore.TargetFetchAdvPropEx"
                      },
                      "TriggerName": "CloseToTrigger"
                    },
                    {
                      "$type": "RPG.GameCore.AdvEnableTrigger",
                      "TargetType": {
                        "$type": "RPG.GameCore.TargetFetchAdvPropEx"
                      },
                      "TriggerName": "ExitTrigger"
                    },
                    {
                      "$type": "RPG.GameCore.TriggerEntityEvent",
                      "EventName": {
                        "Value": "Self_DisableLockInteract"
                      },
                      "InstanceID": {
                        "IsDynamic": false,
                        "FixedValue": {
                          "Value": 0
                        }
                      }
                    },
                    {
                      "$type": "RPG.GameCore.GenericSwitchCase",
                      "SwitchRef": {
                        "$type": "RPG.GameCore.SwitchRefGraphDynamicFloat",
                        "Name": "OpenDir"
                      },
                      "Cases": [
                        {
                          "$type": "RPG.GameCore.NumberCaseContainer",
                          "Case": {
                            "IsDynamic": false,
                            "FixedValue": {
                              "Value": -1
                            }
                          },
                          "OnSuccess": [
                            {
                              "$type": "RPG.GameCore.PredicateTaskList",
                              "Predicate": {
                                "$type": "RPG.GameCore.ByAngle",
                                "From": {
                                  "$type": "RPG.GameCore.TargetFetchAdvPropEx"
                                },
                                "To": {
                                  "$type": "RPG.GameCore.TargetFetchAdvLocalPlayer"
                                },
                                "CompareType": "LessEqual",
                                "CompareValue": {
                                  "IsDynamic": false,
                                  "FixedValue": {
                                    "Value": 180
                                  }
                                }
                              },
                              "SuccessTaskList": [
                                {
                                  "$type": "RPG.GameCore.AnimSetParameter",
                                  "TargetType": {
                                    "$type": "RPG.GameCore.TargetFetchAdvPropEx"
                                  },
                                  "ParameterName": "IsForward",
                                  "ParameterType": "Bool",
                                  "Value": 1
                                },
                                {
                                  "$type": "RPG.GameCore.PropTriggerAnimState",
                                  "AnimStateName": "Opened01",
                                  "TransitionDuration": 0,
                                  "TargetType": {
                                    "$type": "RPG.GameCore.TargetFetchAdvPropEx"
                                  }
                                },
                                {
                                  "$type": "RPG.GameCore.AnimSetParameter",
                                  "TargetType": {
                                    "$type": "RPG.GameCore.TargetFetchAdvPropEx"
                                  },
                                  "ParameterName": "IsOpen",
                                  "ParameterType": "Bool",
                                  "Value": 1
                                },
                                {
                                  "$type": "RPG.GameCore.SetGraphDynamicFloat",
                                  "Name": "Loc_IsOpen",
                                  "TargetIDs": [],
                                  "Value": {
                                    "IsDynamic": false,
                                    "FixedValue": {
                                      "Value": 1
                                    }
                                  }
                                }
                              ],
                              "FailedTaskList": [
                                {
                                  "$type": "RPG.GameCore.AnimSetParameter",
                                  "TargetType": {
                                    "$type": "RPG.GameCore.TargetFetchAdvPropEx"
                                  },
                                  "ParameterName": "IsForward",
                                  "ParameterType": "Bool"
                                },
                                {
                                  "$type": "RPG.GameCore.PropTriggerAnimState",
                                  "AnimStateName": "Opened02",
                                  "TransitionDuration": 0,
                                  "TargetType": {
                                    "$type": "RPG.GameCore.TargetFetchAdvPropEx"
                                  }
                                },
                                {
                                  "$type": "RPG.GameCore.AnimSetParameter",
                                  "TargetType": {
                                    "$type": "RPG.GameCore.TargetFetchAdvPropEx"
                                  },
                                  "ParameterName": "IsOpen",
                                  "ParameterType": "Bool",
                                  "Value": 1
                                },
                                {
                                  "$type": "RPG.GameCore.SetGraphDynamicFloat",
                                  "Name": "Loc_IsOpen",
                                  "TargetIDs": [],
                                  "Value": {
                                    "IsDynamic": false,
                                    "FixedValue": {
                                      "Value": 1
                                    }
                                  }
                                }
                              ]
                            }
                          ]
                        },
                        {
                          "$type": "RPG.GameCore.NumberCaseContainer",
                          "Case": {
                            "IsDynamic": false,
                            "FixedValue": {
                              "Value": 0
                            }
                          },
                          "OnSuccess": [
                            {
                              "$type": "RPG.GameCore.AnimSetParameter",
                              "TargetType": {
                                "$type": "RPG.GameCore.TargetFetchAdvPropEx"
                              },
                              "ParameterName": "IsForward",
                              "ParameterType": "Bool"
                            },
                            {
                              "$type": "RPG.GameCore.PropTriggerAnimState",
                              "AnimStateName": "Opened02",
                              "TransitionDuration": 0,
                              "TargetType": {
                                "$type": "RPG.GameCore.TargetFetchAdvPropEx"
                              }
                            },
                            {
                              "$type": "RPG.GameCore.AnimSetParameter",
                              "TargetType": {
                                "$type": "RPG.GameCore.TargetFetchAdvPropEx"
                              },
                              "ParameterName": "IsOpen",
                              "ParameterType": "Bool",
                              "Value": 1
                            },
                            {
                              "$type": "RPG.GameCore.SetGraphDynamicFloat",
                              "Name": "Loc_IsOpen",
                              "TargetIDs": [],
                              "Value": {
                                "IsDynamic": false,
                                "FixedValue": {
                                  "Value": 1
                                }
                              }
                            }
                          ]
                        },
                        {
                          "$type": "RPG.GameCore.NumberCaseContainer",
                          "Case": {
                            "IsDynamic": false,
                            "FixedValue": {
                              "Value": 1
                            }
                          },
                          "OnSuccess": [
                            {
                              "$type": "RPG.GameCore.AnimSetParameter",
                              "TargetType": {
                                "$type": "RPG.GameCore.TargetFetchAdvPropEx"
                              },
                              "ParameterName": "IsForward",
                              "ParameterType": "Bool",
                              "Value": 1
                            },
                            {
                              "$type": "RPG.GameCore.PropTriggerAnimState",
                              "AnimStateName": "Opened01",
                              "TransitionDuration": 0,
                              "TargetType": {
                                "$type": "RPG.GameCore.TargetFetchAdvPropEx"
                              }
                            },
                            {
                              "$type": "RPG.GameCore.AnimSetParameter",
                              "TargetType": {
                                "$type": "RPG.GameCore.TargetFetchAdvPropEx"
                              },
                              "ParameterName": "IsOpen",
                              "ParameterType": "Bool",
                              "Value": 1
                            },
                            {
                              "$type": "RPG.GameCore.SetGraphDynamicFloat",
                              "Name": "Loc_IsOpen",
                              "TargetIDs": [],
                              "Value": {
                                "IsDynamic": false,
                                "FixedValue": {
                                  "Value": 1
                                }
                              }
                            }
                          ]
                        }
                      ]
                    }
                  ]
                }
              ]
            }
          ]
        }
      ]
    },
    {
      "TaskList": [
        {
          "$type": "RPG.GameCore.WaitEntityEvent",
          "EventName": {
            "Value": "Clt_DebugToggle"
          },
          "OnEvent": [
            {
              "$type": "RPG.GameCore.GenericSwitchCase",
              "SwitchRef": {
                "$type": "RPG.GameCore.SwitchRefPropState"
              },
              "Cases": [
                {
                  "$type": "RPG.GameCore.PropStateCaseContainer",
                  "OnSuccess": [
                    {
                      "$type": "RPG.GameCore.TriggerEntityEvent",
                      "EventName": {
                        "Value": "Clt_TriggerOpen"
                      }
                    }
                  ]
                },
                {
                  "$type": "RPG.GameCore.PropStateCaseContainer",
                  "Case": "Open",
                  "OnSuccess": [
                    {
                      "$type": "RPG.GameCore.TriggerEntityEvent",
                      "EventName": {
                        "Value": "Clt_TriggerLock"
                      }
                    }
                  ]
                },
                {
                  "$type": "RPG.GameCore.PropStateCaseContainer",
                  "Case": "Locked",
                  "OnSuccess": [
                    {
                      "$type": "RPG.GameCore.TriggerEntityEvent",
                      "EventName": {
                        "Value": "Clt_TriggerClose"
                      }
                    }
                  ]
                }
              ]
            }
          ]
        }
      ]
    }
  ],
  "ValueSource": {
    "Values": [
      {
        "$type": "RPG.GameCore.SharedInt",
        "Value": 1,
        "Key": "IsAutoDoor"
      },
      {
        "$type": "RPG.GameCore.SharedString",
        "Value": "PropInteractTitle_10001",
        "Key": "LockToastPile"
      },
      {
        "$type": "RPG.GameCore.SharedInt",
        "Value": 1,
        "Key": "CanInteractInLock"
      },
      {
        "$type": "RPG.GameCore.SharedInt",
        "Key": "Loc_IsOpen"
      },
      {
        "$type": "RPG.GameCore.SharedInt",
        "Value": -1,
        "Key": "OpenDir"
      }
    ]
  },
  "Type": "Entity"
}