{
  "DimensionList": [
    {
      "GroupList": [
        {
          "ID": 1,
          "ConflictSpatialInfo": {
            "CompactGridList": [],
            "LowerUpperBounds": {}
          },
          "StreamingSpatialInfo": {
            "CompactGridList": [],
            "LowerUpperBounds": {}
          },
          "AnchorList": [
            {
              "ID": 1,
              "NavMap": {
                "MapLayerID": 1,
                "AreaID": 1,
                "SectionID": 10000
              },
              "RegionID": 14
            }
          ],
          "RegionIDList": []
        },
        {
          "ID": 2,
          "ConflictSpatialInfo": {
            "CompactGridList": [],
            "LowerUpperBounds": {}
          },
          "StreamingSpatialInfo": {
            "CompactGridList": [
              36,
              -284
            ],
            "LowerUpperBounds": {
              "x": -10,
              "y": -9
            }
          },
          "PropList": [
            {
              "ID": 300001,
              "NavMap": {
                "MapLayerID": 1,
                "AreaID": 1,
                "SectionID": 10000
              },
              "RegionID": 14
            }
          ],
          "AnchorList": [
            {
              "ID": 1,
              "NavMap": {
                "MapLayerID": 3,
                "AreaID": 6,
                "SectionID": 60000
              },
              "RegionID": 18
            },
            {
              "ID": 2,
              "NavMap": {
                "MapLayerID": 1,
                "AreaID": 1,
                "SectionID": 10000
              },
              "RegionID": 14
            },
            {
              "ID": 3,
              "NavMap": {
                "MapLayerID": 1,
                "AreaID": 1,
                "SectionID": 10000
              },
              "RegionID": 14
            }
          ],
          "RegionIDList": [
            14
          ]
        },
        {
          "ID": 3,
          "ConflictSpatialInfo": {
            "CompactGridList": [],
            "LowerUpperBounds": {}
          },
          "StreamingSpatialInfo": {
            "CompactGridList": [
              36,
              -278
            ],
            "LowerUpperBounds": {
              "x": -10,
              "y": -9
            }
          },
          "PropList": [
            {
              "ID": 300001,
              "NavMap": {
                "MapLayerID": 1,
                "AreaID": 1,
                "SectionID": 10000
              },
              "RegionID": 14
            }
          ],
          "RegionIDList": [
            14
          ]
        },
        {
          "ID": 13,
          "ConflictSpatialInfo": {
            "CompactGridList": [],
            "LowerUpperBounds": {}
          },
          "StreamingSpatialInfo": {
            "CompactGridList": [
              -171,
              -50,
              -168,
              -50,
              -162,
              -50,
              -159,
              -50,
              -175,
              -49,
              -177,
              -47,
              -177,
              -44,
              -174,
              -41,
              -171,
              -41,
              -165,
              -41,
              -162,
              -41,
              -159,
              -38,
              -156,
              -35,
              -156,
              -32,
              -156,
              -31
            ],
            "LowerUpperBounds": {
              "x": -5,
              "y": -4
            }
          },
          "PropList": [
            {
              "ID": 300001,
              "NavMap": {
                "MapLayerID": 3,
                "AreaID": 6,
                "SectionID": 60000
              },
              "RegionID": 18
            },
            {
              "ID": 300002,
              "NavMap": {
                "MapLayerID": 3,
                "AreaID": 6,
                "SectionID": 60000
              },
              "RegionID": 18
            },
            {
              "ID": 300010,
              "NavMap": {
                "MapLayerID": 3,
                "AreaID": 6,
                "SectionID": 60000
              },
              "RegionID": 18
            },
            {
              "ID": 300003,
              "NavMap": {
                "MapLayerID": 3,
                "AreaID": 6,
                "SectionID": 60000
              },
              "RegionID": 18
            },
            {
              "ID": 300004,
              "NavMap": {
                "MapLayerID": 3,
                "AreaID": 6,
                "SectionID": 60000
              },
              "RegionID": 18
            },
            {
              "ID": 300005,
              "NavMap": {
                "MapLayerID": 3,
                "AreaID": 6,
                "SectionID": 60000
              },
              "RegionID": 18
            },
            {
              "ID": 300006,
              "NavMap": {
                "MapLayerID": 3,
                "AreaID": 6,
                "SectionID": 60000
              },
              "RegionID": 18
            },
            {
              "ID": 300007,
              "NavMap": {
                "MapLayerID": 3,
                "AreaID": 6,
                "SectionID": 60000
              },
              "RegionID": 18
            },
            {
              "ID": 300008,
              "NavMap": {
                "MapLayerID": 3,
                "AreaID": 6,
                "SectionID": 60000
              },
              "RegionID": 18
            },
            {
              "ID": 300009,
              "NavMap": {
                "MapLayerID": 3,
                "AreaID": 6,
                "SectionID": 60000
              },
              "RegionID": 18
            },
            {
              "ID": 300011,
              "NavMap": {
                "MapLayerID": 3,
                "AreaID": 6,
                "SectionID": 60000
              },
              "RegionID": 18
            },
            {
              "ID": 300012,
              "NavMap": {
                "MapLayerID": 3,
                "AreaID": 6,
                "SectionID": 60000
              },
              "RegionID": 18
            },
            {
              "ID": 300013,
              "NavMap": {
                "MapLayerID": 3,
                "AreaID": 6,
                "SectionID": 60000
              },
              "RegionID": 18
            },
            {
              "ID": 300014,
              "NavMap": {
                "MapLayerID": 3,
                "AreaID": 6,
                "SectionID": 60000
              },
              "RegionID": 18
            },
            {
              "ID": 300015,
              "NavMap": {
                "MapLayerID": 3,
                "AreaID": 6,
                "SectionID": 60000
              },
              "RegionID": 18
            }
          ],
          "RegionIDList": [
            18
          ]
        },
        {
          "ID": 14,
          "ConflictSpatialInfo": {
            "CompactGridList": [],
            "LowerUpperBounds": {}
          },
          "StreamingSpatialInfo": {
            "CompactGridList": [
              -167,
              -47,
              -179,
              -39,
              -159,
              -31
            ],
            "LowerUpperBounds": {
              "x": -14,
              "y": -4
            }
          },
          "PropList": [
            {
              "ID": 300002,
              "NavMap": {
                "MapLayerID": 3,
                "AreaID": 6,
                "SectionID": 60000
              },
              "RegionID": 18
            },
            {
              "ID": 300001,
              "NavMap": {
                "MapLayerID": 3,
                "AreaID": 6,
                "SectionID": 60000
              },
              "RegionID": 18
            },
            {
              "ID": 300003,
              "NavMap": {
                "MapLayerID": 3,
                "AreaID": 6,
                "SectionID": 60000
              },
              "RegionID": 18
            }
          ],
          "RegionIDList": [
            18
          ]
        },
        {
          "ID": 15,
          "ConflictSpatialInfo": {
            "CompactGridList": [],
            "LowerUpperBounds": {}
          },
          "StreamingSpatialInfo": {
            "CompactGridList": [
              -177,
              -53,
              -155,
              -53,
              -167,
              -52,
              -177,
              -26,
              -158,
              -26,
              -155,
              -26
            ],
            "LowerUpperBounds": {
              "x": -14,
              "y": 4
            }
          },
          "PropList": [
            {
              "ID": 300001,
              "NavMap": {
                "MapLayerID": 3,
                "AreaID": 6,
                "SectionID": 60000
              },
              "RegionID": 18
            },
            {
              "ID": 300002,
              "NavMap": {
                "MapLayerID": 3,
                "AreaID": 6,
                "SectionID": 60000
              },
              "RegionID": 18
            },
            {
              "ID": 300004,
              "NavMap": {
                "MapLayerID": 3,
                "AreaID": 6,
                "SectionID": 60000
              },
              "RegionID": 18
            },
            {
              "ID": 300005,
              "NavMap": {
                "MapLayerID": 3,
                "AreaID": 6,
                "SectionID": 60000
              },
              "RegionID": 18
            },
            {
              "ID": 300006,
              "NavMap": {
                "MapLayerID": 3,
                "AreaID": 6,
                "SectionID": 60000
              },
              "RegionID": 18
            },
            {
              "ID": 300003,
              "NavMap": {
                "MapLayerID": 3,
                "AreaID": 6,
                "SectionID": 60000
              },
              "RegionID": 18
            }
          ],
          "RegionIDList": [
            18
          ]
        },
        {
          "ID": 16,
          "ConflictSpatialInfo": {
            "CompactGridList": [],
            "LowerUpperBounds": {}
          },
          "StreamingSpatialInfo": {
            "CompactGridList": [
              -161,
              -26
            ],
            "LowerUpperBounds": {
              "x": 3,
              "y": 4
            }
          },
          "PropList": [
            {
              "ID": 300002,
              "NavMap": {
                "MapLayerID": 3,
                "AreaID": 6,
                "SectionID": 60000
              },
              "RegionID": 18
            }
          ],
          "RegionIDList": [
            18
          ]
        },
        {
          "ID": 17,
          "ConflictSpatialInfo": {
            "CompactGridList": [],
            "LowerUpperBounds": {}
          },
          "StreamingSpatialInfo": {
            "CompactGridList": [
              -174,
              -39,
              -177,
              -30
            ],
            "LowerUpperBounds": {
              "x": 2,
              "y": 5
            }
          },
          "PropList": [
            {
              "ID": 300002,
              "NavMap": {
                "MapLayerID": 3,
                "AreaID": 6,
                "SectionID": 60000
              },
              "RegionID": 18
            },
            {
              "ID": 300001,
              "NavMap": {
                "MapLayerID": 3,
                "AreaID": 6,
                "SectionID": 60000
              },
              "RegionID": 18
            }
          ],
          "RegionIDList": [
            18
          ]
        },
        {
          "ID": 18,
          "ConflictSpatialInfo": {
            "CompactGridList": [],
            "LowerUpperBounds": {}
          },
          "StreamingSpatialInfo": {
            "CompactGridList": [
              -167,
              -50
            ],
            "LowerUpperBounds": {
              "x": 1,
              "y": 2
            }
          },
          "PropList": [
            {
              "ID": 300002,
              "NavMap": {
                "MapLayerID": 3,
                "AreaID": 6,
                "SectionID": 60000
              },
              "RegionID": 18
            }
          ],
          "RegionIDList": [
            18
          ]
        },
        {
          "ID": 19,
          "ConflictSpatialInfo": {
            "CompactGridList": [
              -180,
              -39
            ],
            "LowerUpperBounds": {
              "x": -5,
              "y": -4
            }
          },
          "StreamingSpatialInfo": {
            "CompactGridList": [
              -180,
              -39,
              -179,
              -39,
              -158,
              -31
            ],
            "LowerUpperBounds": {
              "x": -13,
              "y": -4
            }
          },
          "PropList": [
            {
              "ID": 300001,
              "NavMap": {
                "MapLayerID": 3,
                "AreaID": 6,
                "SectionID": 60000
              },
              "RegionID": 18
            },
            {
              "ID": 300002,
              "NavMap": {
                "MapLayerID": 3,
                "AreaID": 6,
                "SectionID": 60000
              },
              "RegionID": 18
            },
            {
              "ID": 300003,
              "NavMap": {
                "MapLayerID": 1
              }
            },
            {
              "ID": 300004,
              "NavMap": {
                "MapLayerID": 1
              }
            },
            {
              "ID": 300005,
              "NavMap": {
                "MapLayerID": 3,
                "AreaID": 6,
                "SectionID": 60000
              },
              "RegionID": 18
            }
          ],
          "NPCList": [
            {
              "ID": 400001,
              "NavMap": {
                "MapLayerID": 3,
                "AreaID": 6,
                "SectionID": 60000
              },
              "RegionID": 18
            }
          ],
          "AnchorList": [
            {
              "ID": 1,
              "NavMap": {
                "MapLayerID": 3,
                "AreaID": 6,
                "SectionID": 60000
              },
              "RegionID": 18
            },
            {
              "ID": 2,
              "NavMap": {
                "MapLayerID": 3,
                "AreaID": 6,
                "SectionID": 60000
              },
              "RegionID": 18
            },
            {
              "ID": 3,
              "NavMap": {
                "MapLayerID": 1
              }
            },
            {
              "ID": 4,
              "NavMap": {
                "MapLayerID": 3,
                "AreaID": 6,
                "SectionID": 60000
              },
              "RegionID": 18
            }
          ],
          "RegionIDList": [
            18
          ]
        },
        {
          "ID": 20,
          "ConflictSpatialInfo": {
            "CompactGridList": [],
            "LowerUpperBounds": {}
          },
          "StreamingSpatialInfo": {
            "CompactGridList": [
              -174,
              -39
            ],
            "LowerUpperBounds": {
              "x": 3,
              "y": 4
            }
          },
          "PropList": [
            {
              "ID": 300001,
              "NavMap": {
                "MapLayerID": 3,
                "AreaID": 6,
                "SectionID": 60000
              },
              "RegionID": 18
            }
          ],
          "RegionIDList": [
            18
          ]
        },
        {
          "ID": 21,
          "ConflictSpatialInfo": {
            "CompactGridList": [],
            "LowerUpperBounds": {}
          },
          "StreamingSpatialInfo": {
            "CompactGridList": [
              -167,
              -49
            ],
            "LowerUpperBounds": {
              "x": 1,
              "y": 2
            }
          },
          "PropList": [
            {
              "ID": 300001,
              "NavMap": {
                "MapLayerID": 3,
                "AreaID": 6,
                "SectionID": 60000
              },
              "RegionID": 18
            }
          ],
          "RegionIDList": [
            18
          ]
        },
        {
          "ID": 28,
          "ConflictSpatialInfo": {
            "CompactGridList": [
              -167,
              -39
            ],
            "LowerUpperBounds": {
              "x": -5,
              "y": -4
            }
          },
          "StreamingSpatialInfo": {
            "CompactGridList": [
              -167,
              -39
            ],
            "LowerUpperBounds": {
              "x": -5,
              "y": -4
            }
          },
          "PropList": [
            {
              "ID": 300001,
              "NavMap": {
                "MapLayerID": 3,
                "AreaID": 6,
                "SectionID": 60000
              },
              "RegionID": 18
            }
          ],
          "NPCList": [
            {
              "ID": 400001,
              "NavMap": {
                "MapLayerID": 3,
                "AreaID": 6,
                "SectionID": 60000
              },
              "RegionID": 18
            }
          ],
          "RegionIDList": [
            18
          ]
        },
        {
          "ID": 29,
          "ConflictSpatialInfo": {
            "CompactGridList": [],
            "LowerUpperBounds": {}
          },
          "StreamingSpatialInfo": {
            "CompactGridList": [
              -179,
              -39
            ],
            "LowerUpperBounds": {
              "x": -5,
              "y": -4
            }
          },
          "PropList": [
            {
              "ID": 300001,
              "NavMap": {
                "MapLayerID": 3,
                "AreaID": 6,
                "SectionID": 60000
              },
              "RegionID": 18
            }
          ],
          "RegionIDList": [
            18
          ]
        },
        {
          "ID": 30,
          "ConflictSpatialInfo": {
            "CompactGridList": [],
            "LowerUpperBounds": {}
          },
          "StreamingSpatialInfo": {
            "CompactGridList": [
              -167,
              -50
            ],
            "LowerUpperBounds": {
              "x": 1,
              "y": 2
            }
          },
          "PropList": [
            {
              "ID": 300001,
              "NavMap": {
                "MapLayerID": 3,
                "AreaID": 6,
                "SectionID": 60000
              },
              "RegionID": 18
            }
          ],
          "AnchorList": [
            {
              "ID": 1,
              "NavMap": {
                "MapLayerID": 3,
                "AreaID": 6,
                "SectionID": 60000
              },
              "RegionID": 18
            }
          ],
          "RegionIDList": [
            18
          ]
        },
        {
          "ID": 31,
          "ConflictSpatialInfo": {
            "CompactGridList": [],
            "LowerUpperBounds": {}
          },
          "StreamingSpatialInfo": {
            "CompactGridList": [
              -174,
              -39
            ],
            "LowerUpperBounds": {
              "x": 2,
              "y": 3
            }
          },
          "PropList": [
            {
              "ID": 300001,
              "NavMap": {
                "MapLayerID": 3,
                "AreaID": 6,
                "SectionID": 60000
              },
              "RegionID": 18
            }
          ],
          "AnchorList": [
            {
              "ID": 1,
              "NavMap": {
                "MapLayerID": 3,
                "AreaID": 6,
                "SectionID": 60000
              },
              "RegionID": 18
            }
          ],
          "RegionIDList": [
            18
          ]
        },
        {
          "ID": 32,
          "ConflictSpatialInfo": {
            "CompactGridList": [],
            "LowerUpperBounds": {}
          },
          "StreamingSpatialInfo": {
            "CompactGridList": [
              -158,
              -30
            ],
            "LowerUpperBounds": {
              "x": -14,
              "y": -13
            }
          },
          "PropList": [
            {
              "ID": 300001,
              "NavMap": {
                "MapLayerID": 3,
                "AreaID": 6,
                "SectionID": 60000
              },
              "RegionID": 18
            }
          ],
          "AnchorList": [
            {
              "ID": 1,
              "NavMap": {
                "MapLayerID": 3,
                "AreaID": 6,
                "SectionID": 60000
              },
              "RegionID": 18
            }
          ],
          "RegionIDList": [
            18
          ]
        },
        {
          "ID": 33,
          "ConflictSpatialInfo": {
            "CompactGridList": [],
            "LowerUpperBounds": {}
          },
          "StreamingSpatialInfo": {
            "CompactGridList": [
              -179,
              -39
            ],
            "LowerUpperBounds": {
              "x": -5,
              "y": -4
            }
          },
          "PropList": [
            {
              "ID": 300001,
              "NavMap": {
                "MapLayerID": 3,
                "AreaID": 6,
                "SectionID": 60000
              },
              "RegionID": 18
            }
          ],
          "RegionIDList": [
            18
          ]
        },
        {
          "ID": 34,
          "ConflictSpatialInfo": {
            "CompactGridList": [],
            "LowerUpperBounds": {}
          },
          "StreamingSpatialInfo": {
            "CompactGridList": [],
            "LowerUpperBounds": {}
          },
          "RegionIDList": []
        },
        {
          "ID": 23,
          "ConflictSpatialInfo": {
            "CompactGridList": [
              -171,
              -53
            ],
            "LowerUpperBounds": {
              "x": -2,
              "y": -1
            }
          },
          "StreamingSpatialInfo": {
            "CompactGridList": [
              -171,
              -53
            ],
            "LowerUpperBounds": {
              "x": -2,
              "y": -1
            }
          },
          "MonsterList": [
            {
              "ID": 200001,
              "NavMap": {
                "MapLayerID": 3,
                "AreaID": 6,
                "SectionID": 60000
              },
              "RegionID": 18
            }
          ],
          "RegionIDList": [
            18
          ]
        },
        {
          "ID": 27,
          "ConflictSpatialInfo": {
            "CompactGridList": [
              -170,
              -26
            ],
            "LowerUpperBounds": {
              "x": -2,
              "y": -1
            }
          },
          "StreamingSpatialInfo": {
            "CompactGridList": [
              -170,
              -26
            ],
            "LowerUpperBounds": {
              "x": -2,
              "y": -1
            }
          },
          "MonsterList": [
            {
              "ID": 200001,
              "NavMap": {
                "MapLayerID": 3,
                "AreaID": 6,
                "SectionID": 60000
              },
              "RegionID": 18
            }
          ],
          "RegionIDList": [
            18
          ]
        },
        {
          "ID": 35,
          "ConflictSpatialInfo": {
            "CompactGridList": [],
            "LowerUpperBounds": {}
          },
          "StreamingSpatialInfo": {
            "CompactGridList": [
              36,
              -284
            ],
            "LowerUpperBounds": {
              "x": -10,
              "y": -9
            }
          },
          "PropList": [
            {
              "ID": 300002,
              "NavMap": {
                "MapLayerID": 1,
                "AreaID": 1,
                "SectionID": 10000
              },
              "RegionID": 14
            }
          ],
          "RegionIDList": [
            14
          ]
        },
        {
          "ID": 37,
          "ConflictSpatialInfo": {
            "CompactGridList": [],
            "LowerUpperBounds": {}
          },
          "StreamingSpatialInfo": {
            "CompactGridList": [],
            "LowerUpperBounds": {}
          },
          "RegionIDList": [
            1,
            2,
            3,
            4,
            5,
            6,
            7,
            8,
            9,
            10,
            11,
            12,
            13,
            14,
            15,
            16,
            17,
            18,
            19,
            20,
            21,
            22,
            23
          ]
        },
        {
          "ID": 38,
          "ConflictSpatialInfo": {
            "CompactGridList": [],
            "LowerUpperBounds": {}
          },
          "StreamingSpatialInfo": {
            "CompactGridList": [],
            "LowerUpperBounds": {}
          },
          "RegionIDList": [
            18
          ]
        },
        {
          "ID": 40,
          "ConflictSpatialInfo": {
            "CompactGridList": [],
            "LowerUpperBounds": {}
          },
          "StreamingSpatialInfo": {
            "CompactGridList": [],
            "LowerUpperBounds": {}
          },
          "RegionIDList": []
        },
        {
          "ID": 41,
          "ConflictSpatialInfo": {
            "CompactGridList": [],
            "LowerUpperBounds": {}
          },
          "StreamingSpatialInfo": {
            "CompactGridList": [],
            "LowerUpperBounds": {}
          },
          "RegionIDList": [
            2,
            4,
            5,
            6,
            7,
            8,
            11,
            12,
            14,
            15,
            16,
            18,
            19,
            20,
            21,
            23
          ]
        },
        {
          "ID": 42,
          "ConflictSpatialInfo": {
            "CompactGridList": [],
            "LowerUpperBounds": {}
          },
          "StreamingSpatialInfo": {
            "CompactGridList": [],
            "LowerUpperBounds": {}
          },
          "RegionIDList": [
            1,
            2,
            3,
            4,
            5,
            6,
            7,
            8,
            9,
            10,
            11,
            12,
            13,
            14,
            15,
            16,
            17,
            19,
            20
          ]
        },
        {
          "ID": 43,
          "ConflictSpatialInfo": {
            "CompactGridList": [],
            "LowerUpperBounds": {}
          },
          "StreamingSpatialInfo": {
            "CompactGridList": [],
            "LowerUpperBounds": {}
          },
          "RegionIDList": []
        },
        {
          "ID": 44,
          "ConflictSpatialInfo": {
            "CompactGridList": [],
            "LowerUpperBounds": {}
          },
          "StreamingSpatialInfo": {
            "CompactGridList": [],
            "LowerUpperBounds": {}
          },
          "RegionIDList": [
            6,
            7,
            9,
            10,
            11,
            12
          ]
        },
        {
          "ID": 45,
          "ConflictSpatialInfo": {
            "CompactGridList": [],
            "LowerUpperBounds": {}
          },
          "StreamingSpatialInfo": {
            "CompactGridList": [],
            "LowerUpperBounds": {}
          },
          "RegionIDList": [
            20
          ]
        },
        {
          "ID": 46,
          "ConflictSpatialInfo": {
            "CompactGridList": [],
            "LowerUpperBounds": {}
          },
          "StreamingSpatialInfo": {
            "CompactGridList": [],
            "LowerUpperBounds": {}
          },
          "RegionIDList": [
            18
          ]
        },
        {
          "ID": 47,
          "ConflictSpatialInfo": {
            "CompactGridList": [],
            "LowerUpperBounds": {}
          },
          "StreamingSpatialInfo": {
            "CompactGridList": [],
            "LowerUpperBounds": {}
          },
          "RegionIDList": [
            15,
            16,
            17
          ]
        },
        {
          "ID": 48,
          "ConflictSpatialInfo": {
            "CompactGridList": [],
            "LowerUpperBounds": {}
          },
          "StreamingSpatialInfo": {
            "CompactGridList": [],
            "LowerUpperBounds": {}
          },
          "RegionIDList": [
            1,
            2,
            3,
            4,
            5
          ]
        }
      ]
    }
  ],
  "Rotatable": {
    "RotatableRegionList": [
      {
        "PoseList": [
          {
            "NavMesh": "Level/NavMesh/NavMesh-Floor_43312003_RotatableRegion0_Pose_Up.asset"
          },
          {
            "NavMesh": "Level/NavMesh/NavMesh-Floor_43312003_RotatableRegion0_Pose_Front.asset"
          },
          {
            "NavMesh": "Level/NavMesh/NavMesh-Floor_43312003_RotatableRegion0_Pose_Back.asset"
          },
          {
            "NavMesh": "Level/NavMesh/NavMesh-Floor_43312003_RotatableRegion0_Pose_Right.asset"
          },
          {
            "NavMesh": "Level/NavMesh/NavMesh-Floor_43312003_RotatableRegion0_Pose_Down.asset"
          },
          {
            "NavMesh": "Level/NavMesh/NavMesh-Floor_43312003_RotatableRegion0_Pose_Left.asset"
          }
        ]
      }
    ]
  },
  "NavMesh": "Level/NavMesh/NavMesh-Floor_20311001.asset"
}