{
  "SaveFile": "Lineup_QuickSave_88",
  "Name": "SAMCE1",
  "SkillTreePreset": "None",
  "SPPreset": "Half",
  "LineupConfigList": [
    {
      "AvatarId": 9104,
      "Level": 79,
      "Promotion": 6,
      "SkillTreePointList": [
        {
          "Id": 9104001,
          "Level": 5
        },
        {
          "Id": 9104002,
          "Level": 8
        },
        {
          "Id": 9104003,
          "Level": 8
        },
        {
          "Id": 9104004,
          "Level": 8
        },
        {
          "Id": 9104007,
          "Level": 1
        },
        {
          "Id": 9104101,
          "Level": 1
        },
        {
          "Id": 9104102,
          "Level": 1
        },
        {
          "Id": 9104103,
          "Level": 1
        },
        {
          "Id": 9104201,
          "Level": 1
        },
        {
          "Id": 9104202,
          "Level": 1
        },
        {
          "Id": 9104203,
          "Level": 1
        },
        {
          "Id": 9104204,
          "Level": 1
        },
        {
          "Id": 9104205,
          "Level": 1
        },
        {
          "Id": 9104206,
          "Level": 1
        },
        {
          "Id": 9104207,
          "Level": 1
        },
        {
          "Id": 9104208,
          "Level": 1
        }
      ],
      "EquipmentConfigList": [
        {
          "Id": 23009,
          "Level": 79,
          "Rank": 3
        }
      ],
      "RelicPropertyTypeList": [
        61070113,
        63059513
      ]
    },
    {
      "AvatarId": 1306,
      "Level": 79,
      "Promotion": 6,
      "SkillTreePointList": [
        {
          "Id": 1306001,
          "Level": 5
        },
        {
          "Id": 1306002,
          "Level": 8
        },
        {
          "Id": 1306003,
          "Level": 8
        },
        {
          "Id": 1306004,
          "Level": 8
        },
        {
          "Id": 1306007,
          "Level": 1
        },
        {
          "Id": 1306101,
          "Level": 1
        },
        {
          "Id": 1306102,
          "Level": 1
        },
        {
          "Id": 1306103,
          "Level": 1
        },
        {
          "Id": 1306201,
          "Level": 1
        },
        {
          "Id": 1306202,
          "Level": 1
        },
        {
          "Id": 1306203,
          "Level": 1
        },
        {
          "Id": 1306204,
          "Level": 1
        },
        {
          "Id": 1306205,
          "Level": 1
        },
        {
          "Id": 1306206,
          "Level": 1
        },
        {
          "Id": 1306207,
          "Level": 1
        },
        {
          "Id": 1306208,
          "Level": 1
        }
      ],
      "EquipmentConfigList": [
        {
          "Id": 21032,
          "Level": 79,
          "Rank": 3
        }
      ],
      "RelicPropertyTypeList": [
        61021113,
        63029913
      ]
    },
    {
      "AvatarId": 1105,
      "Level": 79,
      "Promotion": 6,
      "Rank": 4,
      "SkillTreePointList": [
        {
          "Id": 1105001,
          "Level": 5
        },
        {
          "Id": 1105002,
          "Level": 8
        },
        {
          "Id": 1105003,
          "Level": 8
        },
        {
          "Id": 1105004,
          "Level": 8
        },
        {
          "Id": 1105007,
          "Level": 1
        },
        {
          "Id": 1105101,
          "Level": 1
        },
        {
          "Id": 1105102,
          "Level": 1
        },
        {
          "Id": 1105103,
          "Level": 1
        },
        {
          "Id": 1105201,
          "Level": 1
        },
        {
          "Id": 1105202,
          "Level": 1
        },
        {
          "Id": 1105203,
          "Level": 1
        },
        {
          "Id": 1105204,
          "Level": 1
        },
        {
          "Id": 1105205,
          "Level": 1
        },
        {
          "Id": 1105206,
          "Level": 1
        },
        {
          "Id": 1105207,
          "Level": 1
        },
        {
          "Id": 1105208,
          "Level": 1
        }
      ],
      "EquipmentConfigList": [
        {
          "Id": 21000,
          "Level": 79,
          "Rank": 3
        }
      ],
      "RelicPropertyTypeList": [
        61010313,
        63029913
      ]
    },
    {
      "AvatarId": 1202,
      "Level": 79,
      "Promotion": 6,
      "Rank": 4,
      "SkillTreePointList": [
        {
          "Id": 1202001,
          "Level": 5
        },
        {
          "Id": 1202002,
          "Level": 8
        },
        {
          "Id": 1202003,
          "Level": 8
        },
        {
          "Id": 1202004,
          "Level": 8
        },
        {
          "Id": 1202007,
          "Level": 1
        },
        {
          "Id": 1202101,
          "Level": 1
        },
        {
          "Id": 1202103,
          "Level": 1
        },
        {
          "Id": 1202201,
          "Level": 1
        },
        {
          "Id": 1202202,
          "Level": 1
        },
        {
          "Id": 1202203,
          "Level": 1
        },
        {
          "Id": 1202204,
          "Level": 1
        },
        {
          "Id": 1202205,
          "Level": 1
        },
        {
          "Id": 1202206,
          "Level": 1
        },
        {
          "Id": 1202207,
          "Level": 1
        },
        {
          "Id": 1202208,
          "Level": 1
        },
        {
          "Id": 1202102,
          "Level": 1
        }
      ],
      "EquipmentConfigList": [
        {
          "Id": 21011,
          "Level": 79,
          "Rank": 3
        }
      ],
      "RelicPropertyTypeList": [
        61020713,
        63079913
      ]
    }
  ]
}